setup.py
mcsim/ImportanceSampler.py
mcsim/MCIntegrator.py
mcsim/__init__.py
mcsim/pdfs.py
mcsim.egg-info/PKG-INFO
mcsim.egg-info/SOURCES.txt
mcsim.egg-info/dependency_links.txt
mcsim.egg-info/not-zip-safe
mcsim.egg-info/top_level.txt