Metadata-Version: 1.0
Name: mcsim
Version: 0.1
Summary: Monte Carlo Simulation
Home-page: UNKNOWN
Author: Matthew Edwards
Author-email: UNKNOWN
License: UNKNOWN
Platform: UNKNOWN
